{
  "best_epoch": 18,
  "peak_cpu_memory_MB": 5867.616,
  "peak_gpu_0_memory_MB": 21435,
  "peak_gpu_1_memory_MB": 20139,
  "peak_gpu_2_memory_MB": 20139,
  "peak_gpu_3_memory_MB": 20139,
  "training_duration": "0:09:19.663495",
  "training_start_epoch": 0,
  "training_epochs": 19,
  "epoch": 19,
  "training_accuracy": 0.6972010178117048,
  "training_disc_loss": 0.8997413158416748,
  "training_gen_loss": 6.452726631164551,
  "training_loss": 5.0489349732032185,
  "training_cpu_memory_MB": 5867.616,
  "training_gpu_0_memory_MB": 21435,
  "training_gpu_1_memory_MB": 20139,
  "training_gpu_2_memory_MB": 20139,
  "training_gpu_3_memory_MB": 20139,
  "validation_accuracy": 0.3594704684317719,
  "validation_disc_loss": 3.906252464940471,
  "validation_gen_loss": 7.228044579105992,
  "validation_loss": 6.404810305564634,
  "best_validation_accuracy": 0.37678207739307534,
  "best_validation_disc_loss": 2.0372827399161553,
  "best_validation_gen_loss": 6.98937193809017,
  "best_validation_loss": 5.754125364365116
}