{
  "best_epoch": 0,
  "peak_cpu_memory_MB": 5866.616,
  "peak_gpu_0_memory_MB": 12693,
  "peak_gpu_1_memory_MB": 21433,
  "peak_gpu_2_memory_MB": 10225,
  "peak_gpu_3_memory_MB": 12805,
  "training_duration": "0:00:51.004758",
  "training_start_epoch": 0,
  "training_epochs": 1,
  "epoch": 1,
  "training_accuracy": 0.30788804071246817,
  "training_gen_loss": 3.359052829742432,
  "training_disc_loss": 2.3450191974639893,
  "training_loss": 2.852036027908325,
  "training_cpu_memory_MB": 5866.616,
  "training_gpu_0_memory_MB": 12693,
  "training_gpu_1_memory_MB": 21433,
  "training_gpu_2_memory_MB": 10225,
  "training_gpu_3_memory_MB": 12805,
  "validation_accuracy": 0.31568228105906315,
  "validation_gen_loss": 3.485677807561813,
  "validation_disc_loss": 1.165680907426342,
  "validation_loss": 2.3256793445156467,
  "best_validation_accuracy": 0.3268839103869654,
  "best_validation_gen_loss": 3.894355554734507,
  "best_validation_disc_loss": 1.2119369093448884,
  "best_validation_loss": 2.553146227713554
}