{
  "best_epoch": 12,
  "peak_cpu_memory_MB": 5866.776,
  "peak_gpu_0_memory_MB": 14587,
  "peak_gpu_1_memory_MB": 12805,
  "peak_gpu_2_memory_MB": 14587,
  "peak_gpu_3_memory_MB": 21435,
  "training_duration": "0:08:40.457855",
  "training_start_epoch": 0,
  "training_epochs": 15,
  "epoch": 15,
  "training_accuracy": 0.9440203562340967,
  "training_disc_loss": 0.20311347961425782,
  "training_gen_loss": 5.786314487457275,
  "training_loss": 4.390514240264893,
  "training_cpu_memory_MB": 5866.776,
  "training_gpu_0_memory_MB": 14587,
  "training_gpu_1_memory_MB": 12805,
  "training_gpu_2_memory_MB": 14587,
  "training_gpu_3_memory_MB": 21435,
  "validation_accuracy": 0.3910386965376782,
  "validation_disc_loss": 2.633290350921755,
  "validation_gen_loss": 7.368723706501286,
  "validation_loss": 6.184865381659531,
  "best_validation_accuracy": 0.40020366598778007,
  "best_validation_disc_loss": 2.2909403108968966,
  "best_validation_gen_loss": 7.1231727096123425,
  "best_validation_loss": 5.915114619867588
}