{
  "best_epoch": 7,
  "peak_cpu_memory_MB": 5346.248,
  "peak_gpu_0_memory_MB": 12553,
  "peak_gpu_1_memory_MB": 21435,
  "peak_gpu_2_memory_MB": 0,
  "peak_gpu_3_memory_MB": 12805,
  "training_duration": "0:05:16.469263",
  "training_start_epoch": 0,
  "training_epochs": 8,
  "epoch": 8,
  "training_accuracy": 1.0,
  "training_loss": 0.005756746798467178,
  "training_cpu_memory_MB": 5346.248,
  "training_gpu_0_memory_MB": 12553,
  "training_gpu_1_memory_MB": 21435,
  "training_gpu_2_memory_MB": 0,
  "training_gpu_3_memory_MB": 12805,
  "validation_accuracy": 0.55618950585838,
  "validation_loss": 1.8763352086955638,
  "best_validation_accuracy": 0.5572083545593479,
  "best_validation_loss": 1.8591368237225163
}