{
  "best_epoch": 13,
  "peak_cpu_memory_MB": 5866.692,
  "peak_gpu_0_memory_MB": 22543,
  "peak_gpu_1_memory_MB": 20139,
  "peak_gpu_2_memory_MB": 20139,
  "peak_gpu_3_memory_MB": 20139,
  "training_duration": "0:07:45.976088",
  "training_start_epoch": 0,
  "training_epochs": 16,
  "epoch": 16,
  "training_accuracy": 0.49363867684478374,
  "training_disc_loss": 1.2914320540428161,
  "training_gen_loss": 6.283211879730224,
  "training_loss": 6.284094150249775,
  "training_cpu_memory_MB": 5866.692,
  "training_gpu_0_memory_MB": 22543,
  "training_gpu_1_memory_MB": 20139,
  "training_gpu_2_memory_MB": 20139,
  "training_gpu_3_memory_MB": 20139,
  "validation_accuracy": 0.3625254582484725,
  "validation_disc_loss": 1.8659848705414803,
  "validation_gen_loss": 6.9557936037740395,
  "validation_loss": 6.9587532627967095,
  "best_validation_accuracy": 0.36863543788187375,
  "best_validation_disc_loss": 1.80359943643693,
  "best_validation_gen_loss": 6.950920850999894,
  "best_validation_loss": 6.954005902813327
}