{
  "best_epoch": 2,
  "peak_cpu_memory_MB": 5866.516,
  "peak_gpu_0_memory_MB": 22543,
  "peak_gpu_1_memory_MB": 20139,
  "peak_gpu_2_memory_MB": 20139,
  "peak_gpu_3_memory_MB": 20139,
  "training_duration": "0:03:32.636230",
  "training_start_epoch": 0,
  "training_epochs": 7,
  "epoch": 7,
  "training_accuracy": 0.3333333333333333,
  "training_disc_loss": 1.7389065313339234,
  "training_gen_loss": 6.451218185424804,
  "training_loss": 6.463302538945125,
  "training_cpu_memory_MB": 5866.516,
  "training_gpu_0_memory_MB": 22543,
  "training_gpu_1_memory_MB": 20139,
  "training_gpu_2_memory_MB": 20139,
  "training_gpu_3_memory_MB": 20139,
  "validation_accuracy": 0.34012219959266804,
  "validation_disc_loss": 1.1463935029122136,
  "validation_gen_loss": 6.975221387801632,
  "validation_loss": 6.977894490764987,
  "best_validation_accuracy": 0.3533604887983707,
  "best_validation_disc_loss": 2.8379517120699727,
  "best_validation_gen_loss": 7.476447151553247,
  "best_validation_loss": 7.479283778898178
}