{
  "best_epoch": 5,
  "peak_cpu_memory_MB": 5866.652,
  "peak_gpu_0_memory_MB": 21435,
  "peak_gpu_1_memory_MB": 20139,
  "peak_gpu_2_memory_MB": 20139,
  "peak_gpu_3_memory_MB": 20139,
  "training_duration": "0:04:41.546188",
  "training_start_epoch": 0,
  "training_epochs": 9,
  "epoch": 9,
  "training_accuracy": 0.36895674300254455,
  "training_disc_loss": 1.961072611808777,
  "training_gen_loss": 7.838959636688233,
  "training_loss": 3.1555401728703427,
  "training_cpu_memory_MB": 5866.652,
  "training_gpu_0_memory_MB": 21435,
  "training_gpu_1_memory_MB": 20139,
  "training_gpu_2_memory_MB": 20139,
  "training_gpu_3_memory_MB": 20139,
  "validation_accuracy": 0.3329938900203666,
  "validation_disc_loss": 7.011523915875342,
  "validation_gen_loss": 8.68300485610962,
  "validation_loss": 7.343119021384947,
  "best_validation_accuracy": 0.34826883910386963,
  "best_validation_disc_loss": 4.358399329646941,
  "best_validation_gen_loss": 8.73579474418394,
  "best_validation_loss": 5.228870084208827
}