{
  "best_epoch": 7,
  "peak_cpu_memory_MB": 5867.052,
  "peak_gpu_0_memory_MB": 14587,
  "peak_gpu_1_memory_MB": 13029,
  "peak_gpu_2_memory_MB": 14587,
  "peak_gpu_3_memory_MB": 21435,
  "training_duration": "0:04:34.444187",
  "training_start_epoch": 0,
  "training_epochs": 7,
  "epoch": 7,
  "training_accuracy": 0.628498727735369,
  "training_disc_loss": 0.9443153184652329,
  "training_gen_loss": 6.044354963302612,
  "training_loss": 4.769345083236694,
  "training_cpu_memory_MB": 5867.052,
  "training_gpu_0_memory_MB": 14587,
  "training_gpu_1_memory_MB": 13029,
  "training_gpu_2_memory_MB": 14587,
  "training_gpu_3_memory_MB": 21435,
  "validation_accuracy": 0.3910386965376782,
  "validation_disc_loss": 1.5363273979202519,
  "validation_gen_loss": 6.974486878247765,
  "validation_loss": 5.614946977878974,
  "best_validation_accuracy": 0.3910386965376782,
  "best_validation_disc_loss": 1.5363273979202519,
  "best_validation_gen_loss": 6.974486878247765,
  "best_validation_loss": 5.614946977878974
}