{
  "best_epoch": 3,
  "peak_cpu_memory_MB": 5355.548,
  "peak_gpu_0_memory_MB": 12593,
  "peak_gpu_1_memory_MB": 21435,
  "peak_gpu_2_memory_MB": 0,
  "peak_gpu_3_memory_MB": 12815,
  "training_duration": "0:04:11.672652",
  "training_start_epoch": 0,
  "training_epochs": 6,
  "epoch": 6,
  "training_accuracy": 0.9923664122137404,
  "training_loss": 0.02570498247559254,
  "training_cpu_memory_MB": 5355.548,
  "training_gpu_0_memory_MB": 12593,
  "training_gpu_1_memory_MB": 21435,
  "training_gpu_2_memory_MB": 0,
  "training_gpu_3_memory_MB": 12815,
  "validation_accuracy": 0.584411614875191,
  "validation_loss": 1.545009046501756,
  "best_validation_accuracy": 0.6133469179826796,
  "best_validation_loss": 1.3355672223560198
}