{
  "best_epoch": 26,
  "peak_cpu_memory_MB": 5866.568,
  "peak_gpu_0_memory_MB": 21435,
  "peak_gpu_1_memory_MB": 20139,
  "peak_gpu_2_memory_MB": 20139,
  "peak_gpu_3_memory_MB": 20139,
  "training_duration": "0:12:26.758842",
  "training_start_epoch": 0,
  "training_epochs": 26,
  "epoch": 26,
  "training_accuracy": 0.6641221374045801,
  "training_disc_loss": 0.7592142975330353,
  "training_gen_loss": 6.240014839172363,
  "training_loss": 5.7056008118849535,
  "training_cpu_memory_MB": 5866.568,
  "training_gpu_0_memory_MB": 21435,
  "training_gpu_1_memory_MB": 20139,
  "training_gpu_2_memory_MB": 20139,
  "training_gpu_3_memory_MB": 20139,
  "validation_accuracy": 0.4134419551934827,
  "validation_disc_loss": 1.5868642714715773,
  "validation_gen_loss": 6.866465945397654,
  "validation_loss": 6.3412937964162515,
  "best_validation_accuracy": 0.4134419551934827,
  "best_validation_disc_loss": 1.5868642714715773,
  "best_validation_gen_loss": 6.866465945397654,
  "best_validation_loss": 6.3412937964162515
}