{
  "best_epoch": 4,
  "peak_cpu_memory_MB": 5867.244,
  "peak_gpu_0_memory_MB": 13845,
  "peak_gpu_1_memory_MB": 13005,
  "peak_gpu_2_memory_MB": 13845,
  "peak_gpu_3_memory_MB": 21435,
  "training_duration": "0:03:14.402268",
  "training_start_epoch": 0,
  "training_epochs": 5,
  "epoch": 5,
  "training_accuracy": 0.5063613231552163,
  "training_disc_loss": 1.2050197750329972,
  "training_gen_loss": 6.0173145771026615,
  "training_loss": 6.0173145771026615,
  "training_cpu_memory_MB": 5867.244,
  "training_gpu_0_memory_MB": 13845,
  "training_gpu_1_memory_MB": 13005,
  "training_gpu_2_memory_MB": 13845,
  "training_gpu_3_memory_MB": 21435,
  "validation_accuracy": 0.3615071283095723,
  "validation_disc_loss": 1.5654018293551313,
  "validation_gen_loss": 7.181307265428993,
  "validation_loss": 7.181307265428993,
  "best_validation_accuracy": 0.3859470468431772,
  "best_validation_disc_loss": 1.3518280159167158,
  "best_validation_gen_loss": 6.930312114033272,
  "best_validation_loss": 6.930312114033272
}