{
  "best_epoch": 14,
  "peak_cpu_memory_MB": 5866.56,
  "peak_gpu_0_memory_MB": 13845,
  "peak_gpu_1_memory_MB": 12805,
  "peak_gpu_2_memory_MB": 13845,
  "peak_gpu_3_memory_MB": 21435,
  "training_duration": "0:11:10.068740",
  "training_start_epoch": 0,
  "training_epochs": 19,
  "epoch": 19,
  "training_accuracy": 0.727735368956743,
  "training_disc_loss": 0.7744744588248431,
  "training_gen_loss": 5.465723304748535,
  "training_loss": 5.465723304748535,
  "training_cpu_memory_MB": 5866.56,
  "training_gpu_0_memory_MB": 13845,
  "training_gpu_1_memory_MB": 12805,
  "training_gpu_2_memory_MB": 13845,
  "training_gpu_3_memory_MB": 21435,
  "validation_accuracy": 0.3818737270875764,
  "validation_disc_loss": 2.1325596071840303,
  "validation_gen_loss": 8.029092722791967,
  "validation_loss": 8.029092722791967,
  "best_validation_accuracy": 0.39613034623217924,
  "best_validation_disc_loss": 1.4518694472991354,
  "best_validation_gen_loss": 7.879490856232682,
  "best_validation_loss": 7.879490856232682
}