{
  "best_epoch": 10,
  "peak_cpu_memory_MB": 5866.188,
  "peak_gpu_0_memory_MB": 21435,
  "peak_gpu_1_memory_MB": 20139,
  "peak_gpu_2_memory_MB": 20139,
  "peak_gpu_3_memory_MB": 20139,
  "training_duration": "0:04:52.200983",
  "training_start_epoch": 0,
  "training_epochs": 10,
  "epoch": 10,
  "training_accuracy": 0.45038167938931295,
  "training_disc_loss": 1.3632402753829955,
  "training_gen_loss": 6.641199645996093,
  "training_loss": 5.313238290640024,
  "training_cpu_memory_MB": 5866.188,
  "training_gpu_0_memory_MB": 21435,
  "training_gpu_1_memory_MB": 20139,
  "training_gpu_2_memory_MB": 20139,
  "training_gpu_3_memory_MB": 20139,
  "validation_accuracy": 0.35845213849287166,
  "validation_disc_loss": 2.277599153018767,
  "validation_gen_loss": 7.007495472508092,
  "validation_loss": 5.829715728759766,
  "best_validation_accuracy": 0.35845213849287166,
  "best_validation_disc_loss": 2.277599153018767,
  "best_validation_gen_loss": 7.007495472508092,
  "best_validation_loss": 5.829715728759766
}